BoPlotKit/__init__.py
BoPlotKit/config.py
BoPlotKit/curves.py
BoPlotKit/heatmap.py
BoPlotKit/schematic_particles.py
BoPlotKit/style.py
BoPlotKit/utils.py
boplotkit-0.1.7.dist-info/licenses/LICENSE
boplotkit-0.1.7.dist-info/METADATA
boplotkit-0.1.7.dist-info/WHEEL
boplotkit-0.1.7.dist-info/top_level.txt
boplotkit-0.1.7.dist-info/RECORD
