Metadata-Version: 2.4
Name: BoPlotKit
Version: 0.1.7
Summary: An advanced and flexible scientific plotting toolkit.
Home-page: https://github.com/bo-qian/BoPlotKit
Author: Bo Qian
Author-email: Bo Qian <bqian@shu.edu.cn>
License: GNU General Public License v3 (GPLv3)
Project-URL: Homepage, https://github.com/bo-qian/BoPlotKit
Project-URL: Repository, https://github.com/bo-qian/BoPlotKit
Requires-Python: >=3.8
License-File: LICENSE
Requires-Dist: matplotlib>=3.0
Requires-Dist: numpy>=1.18
Requires-Dist: pandas>=1.0
Requires-Dist: pytest>=6.0
Dynamic: author
Dynamic: home-page
Dynamic: license-file
Dynamic: requires-python
